README.md
setup.py
minecraft_movie_player/__init__.py
minecraft_movie_player/__main__.py
minecraft_movie_player/cli.py
minecraft_movie_player/controller.py
minecraft_movie_player/image_converter.py
minecraft_movie_player/index.txt
minecraft_movie_player/palette.txt
minecraft_movie_player/palette_generator.py
minecraft_movie_player/player_functions.py
minecraft_movie_player/player_maker.py
minecraft_movie_player/player_resourcepack.py
minecraft_movie_player/structure_block.py
minecraft_movie_player.egg-info/PKG-INFO
minecraft_movie_player.egg-info/SOURCES.txt
minecraft_movie_player.egg-info/dependency_links.txt
minecraft_movie_player.egg-info/entry_points.txt
minecraft_movie_player.egg-info/requires.txt
minecraft_movie_player.egg-info/top_level.txt