Metadata-Version: 2.1
Name: minecraft-movie-player
Version: 0.1.2
Summary: A command line program that generates a datapack that plays videos in vanilla Minecraft
Home-page: https://github.com/Naratna/minecraft-movie-player
Author: Naratna
Author-email: antar.espadas@hotmail.com
License: MIT
Platform: UNKNOWN
Classifier: Programming Language :: Python :: 3
Classifier: License :: OSI Approved :: MIT License
Classifier: Operating System :: OS Independent
Requires-Python: >=3.8
